MANIFEST.in
README.md
requirements.txt
setup.cfg
setup.py
exposing/EE.py
exposing/Exposer.py
exposing/__init__.py
exposing/_version.py
exposing.egg-info/PKG-INFO
exposing.egg-info/SOURCES.txt
exposing.egg-info/dependency_links.txt
exposing.egg-info/requires.txt
exposing.egg-info/top_level.txt
exposing/tests/__init__.py
exposing/tests/test_common.py
exposing/tests/test_exposing.py
exposing/tests/test_streaming.py